tough/__init__.py
tough/__main__.py
tough/config.py
tough/eol_mapper.py
tough/opener.py
tough/tough.py
tough/utils.py
tough/commands/__init__.py
tough/commands/reindex.py
tough/commands/search.py
toughsearch-0.1.0.dist-info/LICENSE
toughsearch-0.1.0.dist-info/METADATA
toughsearch-0.1.0.dist-info/WHEEL
toughsearch-0.1.0.dist-info/top_level.txt
toughsearch-0.1.0.dist-info/RECORD
