Metadata-Version: 2.1
Name: toughsearch
Version: 0.1.0
Summary: Simple date-based search engine for text- and gzip-logs
Home-page: https://github.com/toughsearch/tough
Author: Dmitriy Doroshev
Author-email: r.schweppes@ya.ru
License: UNKNOWN
Platform: UNKNOWN
Classifier: Programming Language :: Python :: 3.6
Classifier: Programming Language :: Python :: 3.7
Classifier: License :: OSI Approved :: MIT License
Requires-Dist: indexed-gzip (~=0.8.10)
Requires-Dist: pyyaml (~=5.1.1)
Requires-Dist: tqdm (~=4.31.1)
